vipe-0.5.3.dist-info/METADATA
vipe-0.5.3.dist-info/top_level.txt
vipe-0.5.3.dist-info/metadata.json
vipe-0.5.3.dist-info/RECORD
vipe-0.5.3.dist-info/DESCRIPTION.rst
vipe-0.5.3.dist-info/WHEEL
vipe-0.5.3.data/scripts/vipe-oozie2oozie_yaml
vipe-0.5.3.data/scripts/vipe-pipeline2dot
vipe-0.5.3.data/scripts/vipe-oozie_yaml2pipeline
vipe-0.5.3.data/scripts/vipe-oozie2png
vipe-0.5.3.data/scripts/vipe-dot2png
vipe/RELEASE-VERSION~
vipe/__init__.py
vipe/RELEASE-VERSION
vipe/oozie2png.py
vipe/oozie/__init__.py
vipe/oozie/graph.py
vipe/oozie/converter/iis.py
vipe/oozie/converter/converter.py
vipe/oozie/converter/__init__.py
vipe/oozie/converter/__pycache__/__init__.cpython-34.pyc
vipe/oozie/converter/__pycache__/iis.cpython-34.pyc
vipe/oozie/converter/__pycache__/converter.cpython-34.pyc
vipe/oozie/converter/test/test_iis_converter.py
vipe/oozie/converter/test/test_iis_ports_from_configuration_retriever.py
vipe/oozie/converter/test/__pycache__/test_iis_ports_from_configuration_retriever.cpython-34-PYTEST.pyc
vipe/oozie/converter/test/__pycache__/test_iis_converter.cpython-34-PYTEST.pyc
vipe/oozie/__pycache__/graph.cpython-34.pyc
vipe/oozie/__pycache__/__init__.cpython-34.pyc
vipe/oozie/test/data/run_oozie_yaml2pipeline_tmp.sh
vipe/oozie/test/data/run_oozie2oozie_yaml_on_workflows.sh
vipe/oozie/test/data/run_oozie_yaml2pipeline_on_workflows.sh
vipe/oozie/test/data/run_oozie2oozie_yaml_on_workflows_tmp.sh
vipe/oozie/test/data/hadoopstreaming/workflow.yaml
vipe/oozie/test/data/hadoopstreaming/pipeline.yaml
vipe/oozie/test/data/hadoopstreaming/workflow.xml
vipe/oozie/test/data/java/workflow.yaml
vipe/oozie/test/data/java/pipeline.yaml
vipe/oozie/test/data/java/workflow.xml
vipe/oozie/test/data/generateschema/workflow.yaml
vipe/oozie/test/data/generateschema/pipeline.yaml
vipe/oozie/test/data/generateschema/workflow.xml
vipe/oozie/test/data/pig-implicitly_named_ports/workflow.yaml
vipe/oozie/test/data/pig-implicitly_named_ports/pipeline.yaml
vipe/oozie/test/data/pig-implicitly_named_ports/workflow.xml
vipe/oozie/test/data/subworkflow_with_root_ports/workflow.yaml
vipe/oozie/test/data/subworkflow_with_root_ports/pipeline.yaml
