Metadata-Version: 2.0
Name: vipe
Version: 0.5.3
Summary: Tool for visualizing Apache Oozie pipelines
Home-page: https://github.com/openaire/vipe
Author: Mateusz Kobos
Author-email: mkobos@icm.edu.pl
License: Apache License, Version 2.0
Keywords: Oozie,workflow visualization,pipeline visualization
Platform: UNKNOWN
Classifier: Development Status :: 2 - Pre-Alpha
Classifier: Environment :: Console
Classifier: Intended Audience :: Developers
Classifier: Programming Language :: Python
Classifier: Programming Language :: Python :: 3.4
Classifier: License :: OSI Approved :: Apache Software License
Classifier: Topic :: Scientific/Engineering :: Visualization
Requires-Dist: pyyaml
Requires-Dist: pytest
